plot_ann.py
plot_ann-1.1.3.dist-info/METADATA
plot_ann-1.1.3.dist-info/WHEEL
plot_ann-1.1.3.dist-info/top_level.txt
plot_ann-1.1.3.dist-info/RECORD
