Metadata-Version: 2.1
Name: plot-ann
Version: 1.1.3
Summary: Plot an Artificial Neural Network (ANN) model
Home-page: UNKNOWN
Author: Marco Necci
License: MIT License
Platform: UNKNOWN
Requires-Dist: matplotlib
Requires-Dist: numpy
